pykath/__init__.py
pykath/pykath.py
PyKATh-0.1.2.dist-info/LICENSE
PyKATh-0.1.2.dist-info/METADATA
PyKATh-0.1.2.dist-info/WHEEL
PyKATh-0.1.2.dist-info/top_level.txt
PyKATh-0.1.2.dist-info/RECORD
