Metadata-Version: 2.1
Name: PyKATh
Version: 0.1.2
Summary: This library assists in the creation of signed Knox Cloud Access Tokens using python.
Home-page: https://github.com/mattintech/PyKATh
Author: Matt Hills
Author-email: Matt Hills <mattintech@gmail.com>
Project-URL: Homepage, https://github.com/mattintech/PyKATh
Project-URL: Issues, https://github.com/mattintech/PyKATh/issues
Classifier: Programming Language :: Python :: 3
Classifier: License :: OSI Approved :: MIT License
Classifier: Operating System :: OS Independent
Requires-Python: >=3.8
License-File: LICENSE
Requires-Dist: requests
Requires-Dist: PyKTL
